[
  {
    "name": "Experts advise against prostate cancer screening for most men in UK",
    "link": "https://www.youtube.com/embed/OCXZU8uFE18"
  },
  {
    "name": "Famous names affected by prostate cancer criticise NHS screening decision",
    "link": "https://www.youtube.com/embed/vCZguM6aMFA"
  },
  {
    "name": "Prostate Cancer Screening: UK Experts Recommend Against Routine Testing for Most Men",
    "link": "https://www.youtube.com/embed/t39I8cdhynw"
  },
  {
    "name": "Why Experts Are Advising Against Routine Prostate Cancer Screening for Most Men in the UK",
    "link": "https://www.youtube.com/embed/t_PfyZM9F30"
  }
]