[
  {
    "name": "Judge rules Trump admin&#39;s National Guard deployment in DC illegal | LiveNOW from FOX",
    "link": "https://www.youtube.com/embed/VTgGnGmFbmA"
  },
  {
    "name": "What&#39;s next in Portland after court rules Trump can deploy troops?",
    "link": "https://www.youtube.com/embed/bFJ1pZ0FLLA"
  },
  {
    "name": "Trump’s National Guard deployment to Portland blocked by judge",
    "link": "https://www.youtube.com/embed/ZwDVLqMx19M"
  },
  {
    "name": "Federal judge permanently bars Trump administration from deploying National Guard troops to Portland",
    "link": "https://www.youtube.com/embed/4AC5eto5wTo"
  }
]