[
  {
    "name": "UK Budget: Reeves Set To Unveil Budget &amp; New Fed Chair Frontrunner | Daybreak Europe 11/26/2025",
    "link": "https://www.youtube.com/embed/mk8O8rMyngk"
  },
  {
    "name": "The Open for Wednesday, Nov. 26, 2025",
    "link": "https://www.youtube.com/embed/KGpeV7KJBRs"
  },
  {
    "name": "Can A Gummy Bear Break Your Fall? 🤔",
    "link": "https://www.youtube.com/embed/QumvUiS80Yk"
  },
  {
    "name": "Gary Shilling explains the only way to beat the market and win",
    "link": "https://www.youtube.com/embed/w9QoCKbx6d8"
  }
]